whattime/__init__.py
whattime/base.py
whattime/day.py
whattime/type.py
whattime/utils.py
whattime/week.py
whattime-0.1.0.dist-info/AUTHORS.rst
whattime-0.1.0.dist-info/LICENSE.txt
whattime-0.1.0.dist-info/METADATA
whattime-0.1.0.dist-info/WHEEL
whattime-0.1.0.dist-info/top_level.txt
whattime-0.1.0.dist-info/RECORD
