Metadata-Version: 2.1
Name: whattime
Version: 0.1.0
Summary: Checking what kind of time a date is.
Home-page: https://github.com/grammofy/whattime
Author: Paul Götze
Author-email: paul.christoph.goetze@gmail.com
Maintainer: Paul Götze
Maintainer-email: paul.christoph.goetze@gmail.com
License: MIT
Platform: any
Classifier: Development Status :: 4 - Beta
Classifier: Topic :: Utilities
Classifier: Programming Language :: Python
Classifier: Intended Audience :: Developers
Classifier: License :: OSI Approved :: MIT License
Classifier: Operating System :: POSIX :: Linux
Classifier: Operating System :: Unix
Classifier: Operating System :: MacOS
Classifier: Operating System :: Microsoft :: Windows
Provides-Extra: testing
Requires-Dist: pytest ; extra == 'testing'
Requires-Dist: pytest-cov ; extra == 'testing'
Requires-Dist: pytest-randomly ; extra == 'testing'
